naukri_scraper/__init__.py
naukri_scraper/cookies.py
naukri_scraper/headers.py
naukri_scraper/scraper.py
naukri_scraper-0.1.0.dist-info/licenses/LICENSE
naukri_scraper-0.1.0.dist-info/METADATA
naukri_scraper-0.1.0.dist-info/WHEEL
naukri_scraper-0.1.0.dist-info/entry_points.txt
naukri_scraper-0.1.0.dist-info/top_level.txt
naukri_scraper-0.1.0.dist-info/RECORD
