Metadata-Version: 2.4
Name: naukri-scraper
Version: 0.1.0
Summary: A tool for scraping job listings from Naukri.com
Home-page: https://github.com/pawankumar941394/naukri-scraper
Author: Pawan Kumar
Author-email: pawan941394@gmail.com
Project-URL: Bug Tracker, https://github.com/pawankumar941394/naukri-scraper/issues
Project-URL: YouTube Channel, https://www.youtube.com/@Pawankumar-py4tk
Classifier: Programming Language :: Python :: 3
Classifier: License :: OSI Approved :: MIT License
Classifier: Operating System :: OS Independent
Classifier: Development Status :: 4 - Beta
Classifier: Intended Audience :: Developers
Classifier: Topic :: Internet :: WWW/HTTP :: Indexing/Search
Requires-Python: >=3.6
License-File: LICENSE
Requires-Dist: requests>=2.0.0
Dynamic: author
Dynamic: author-email
Dynamic: classifier
Dynamic: description
Dynamic: description-content-type
Dynamic: home-page
Dynamic: license-file
Dynamic: project-url
Dynamic: requires-dist
Dynamic: requires-python
Dynamic: summary
